artblog/__init__.py
artblog/__main__.py
artblog/artblog.py
artblog/config/config.yml
artblog/css/style.css
artblog/html/base.html
artblog/html/license.html
artblog-0.3.0.dist-info/LICENSE
artblog-0.3.0.dist-info/METADATA
artblog-0.3.0.dist-info/WHEEL
artblog-0.3.0.dist-info/entry_points.txt
artblog-0.3.0.dist-info/top_level.txt
artblog-0.3.0.dist-info/RECORD
