Metadata-Version: 2.1
Name: artblog
Version: 0.3.0
Summary: Static site generator for simple personal art/picture/photo blogs.
Home-page: https://github.com/ravi-chandran/artblog
Author: Ravi Chandran
License: UNKNOWN
Platform: UNKNOWN
Classifier: Programming Language :: Python :: 3
Classifier: License :: OSI Approved :: MIT License
Classifier: Operating System :: OS Independent
Requires-Python: >=3.6
License-File: LICENSE
Requires-Dist: requests
Requires-Dist: pyyaml
Requires-Dist: mistune (==2.0.0rc1)
